examples/00_basic_points_vectors.py
examples/01_polygon_area_centroid.py
examples/02_convex_hull_demo.py
examples/03_boolean_clipping.py
examples/04_intersections_3d.py
examples/05_triangulation_demo.py
examples/__init__.py
geo/__init__.py
geo/core/__init__.py
geo/core/point.py
geo/core/precision.py
geo/core/transform.py
geo/core/vector.py
geo/operations/__init__.py
geo/operations/boolean_ops.py
geo/operations/containment.py
geo/operations/convex_hull.py
geo/operations/intersections_2d.py
geo/operations/intersections_3d.py
geo/operations/measurements.py
geo/operations/triangulation.py
geo/primitives_2d/__init__.py
geo/primitives_2d/circle.py
geo/primitives_2d/ellipse.py
geo/primitives_2d/line.py
geo/primitives_2d/polygon.py
geo/primitives_2d/rectangle.py
geo/primitives_2d/triangle.py
geo/primitives_2d/curve/__init__.py
geo/primitives_2d/curve/base.py
geo/primitives_2d/curve/bezier.py
geo/primitives_2d/curve/spline.py
geo/primitives_3d/__init__.py
geo/primitives_3d/cone.py
geo/primitives_3d/cube.py
geo/primitives_3d/cylinder.py
geo/primitives_3d/line_3d.py
geo/primitives_3d/plane.py
geo/primitives_3d/polyhedra.py
geo/primitives_3d/sphere.py
geo/utils/__init__.py
geo/utils/io.py
geo/utils/validators.py
geo-1.0.1.dist-info/licenses/LICENSE
tests/__init__.py
tests/conftest.py
tests/core/__init__.py
tests/core/test_point.py
tests/core/test_precision.py
tests/core/test_transform.py
tests/core/test_vector.py
tests/operations/__init__.py
tests/operations/test_boolean_ops.py
tests/operations/test_containment.py
tests/operations/test_convex_hull.py
tests/operations/test_intersections_2d.py
tests/operations/test_intersections_3d.py
tests/operations/test_measurements.py
tests/operations/test_triangulation.py
tests/primitives_2d/__init__.py
tests/primitives_2d/test_circle.py
tests/primitives_2d/test_ellipse.py
tests/primitives_2d/test_line.py
tests/primitives_2d/test_polygon.py
tests/primitives_2d/test_rectangle.py
tests/primitives_2d/test_triangle.py
tests/primitives_2d/curve/__init__.py
geo-1.0.1.dist-info/METADATA
geo-1.0.1.dist-info/WHEEL
geo-1.0.1.dist-info/top_level.txt
geo-1.0.1.dist-info/RECORD
